[
  {
    "question": "I need to ______ early tomorrow.",
    "options": [
      "wake up",
      "wake down",
      "wake out",
      "wake in"
    ],
    "correct": "wake up",
    "explanation": "<Wake up> means to stop sleeping and become awake."
  },
  {
    "question": "Please ______ the TV. It's too loud.",
    "options": [
      "turn at",
      "turn up",
      "turn in",
      "turn down"
    ],
    "correct": "turn down",
    "explanation": "<Turn down> means to reduce the volume."
  },
  {
    "question": "Can you ______ this word in the dictionary?",
    "options": [
      "look at",
      "look in",
      "look up",
      "look down"
    ],
    "correct": "look up",
    "explanation": "<Look up> means to search for information."
  },
  {
    "question": "I ______ at 7 AM every day.",
    "options": [
      "get at",
      "get down",
      "get in",
      "get up"
    ],
    "correct": "get up",
    "explanation": "<Get up> means to rise from bed."
  },
  {
    "question": "Please ______ your shoes before entering.",
    "options": [
      "take up",
      "take off",
      "take down",
      "take on"
    ],
    "correct": "take off",
    "explanation": "<Take off> means to remove clothing or shoes."
  },
  {
    "question": "I need to ______ my homework.",
    "options": [
      "hand in",
      "hand up",
      "give up",
      "give in"
    ],
    "correct": "hand in",
    "explanation": "<Hand in> means to submit or deliver something."
  },
  {
    "question": "Let's ______ the meeting until tomorrow.",
    "options": [
      "put up",
      "put down",
      "put on",
      "put off"
    ],
    "correct": "put off",
    "explanation": "<Put off> means to postpone or delay."
  },
  {
    "question": "Can you ______ the lights, please?",
    "options": [
      "turn off",
      "turn down",
      "turn at",
      "turn up"
    ],
    "correct": "turn off",
    "explanation": "<Turn off> means to stop a device from operating."
  },
  {
    "question": "I ______ my old friend yesterday.",
    "options": [
      "ran into",
      "ran off",
      "ran up",
      "ran down"
    ],
    "correct": "ran into",
    "explanation": "Run into means to meet someone by chance. <Ran into> is the past simple form of <Run into>."
  },
  {
    "question": "Please ______ the form.",
    "options": [
      "fill down",
      "fill in",
      "fill up",
      "fill at"
    ],
    "correct": "fill in",
    "explanation": "<Fill in> means to complete a form with information."
  },
  {
    "question": "I need to ______ some money from the bank.",
    "options": [
      "take down",
      "take in",
      "take out",
      "take up"
    ],
    "correct": "take out",
    "explanation": "<Take out> means to withdraw money."
  },
  {
    "question": "Let's ______ this problem together.",
    "options": [
      "work down",
      "work up",
      "work out",
      "work in"
    ],
    "correct": "work out",
    "explanation": "<Work out> means to solve or resolve."
  },
  {
    "question": "I ______ my jacket because it was cold.",
    "options": [
      "put off",
      "put on",
      "put down",
      "put up"
    ],
    "correct": "put on",
    "explanation": "<Put on> means to dress yourself in clothing."
  },
  {
    "question": "Can you ______ the music? I can't hear it.",
    "options": [
      "turn down",
      "turn up",
      "turn in",
      "turn off"
    ],
    "correct": "turn up",
    "explanation": "<Turn up> means to increase the volume."
  },
  {
    "question": "I need to ______ my room.",
    "options": [
      "clean down",
      "clean up",
      "clean in",
      "clean at"
    ],
    "correct": "clean up",
    "explanation": "<Clean up> means to tidy or organize."
  },
  {
    "question": "Please ______ for a moment.",
    "options": [
      "sit in",
      "sit up",
      "sit at",
      "sit down"
    ],
    "correct": "sit down",
    "explanation": "<Sit down> means to take a seat."
  },
  {
    "question": "I ______ smoking last year.",
    "options": [
      "gave in",
      "gave out",
      "gave off",
      "gave up"
    ],
    "correct": "gave up",
    "explanation": "Give up means to stop doing something. <Gave up> is the past simple form of <Give up>."
  },
  {
    "question": "Let's ______ the party at 10 PM.",
    "options": [
      "go out",
      "go on",
      "go off",
      "go away"
    ],
    "correct": "go away",
    "explanation": "<Go away> means to leave a place."
  },
  {
    "question": "I need to ______ my email.",
    "options": [
      "check up",
      "check in",
      "check on",
      "check out"
    ],
    "correct": "check out",
    "explanation": "<Check out> means to examine or review."
  },
  {
    "question": "Please ______ the door when you leave.",
    "options": [
      "close down",
      "close in",
      "close off",
      "close up"
    ],
    "correct": "close up",
    "explanation": "<Close up> means to shut completely."
  }
]
