[
  {
    "en": "Feeling blue",
    "es": "Sentirse triste / Deprimido",
    "ipa": "/ˈfiːlɪŋ bluː/",
    "example": "She's feeling blue today.",
    "example_es": "Se siente triste hoy."
  },
  {
    "en": "Cold feet",
    "es": "Echarse para atrás / Acobardarse",
    "ipa": "/koʊld fiːt/",
    "example": "He's got cold feet about the presentation.",
    "example_es": "Se ha echado para atrás con la presentación."
  },
  {
    "en": "Butterflies in your stomach",
    "es": "Tener mariposas en el estómago",
    "ipa": "/ˈbʌtərflaɪz ɪn jɔːr ˈstʌmək/",
    "example": "She's got butterflies in her stomach.",
    "example_es": "Tiene mariposas en el estómago."
  },
  {
    "en": "A short fuse",
    "es": "Tener poca paciencia / Ser irascible",
    "ipa": "/ə ʃɔːrt fjuːz/",
    "example": "He's got a short fuse.",
    "example_es": "Tiene poca paciencia."
  },
  {
    "en": "A heavy heart",
    "es": "Con el corazón encogido / Triste",
    "ipa": "/ə ˈhevi hɑːrt/",
    "example": "She's got a heavy heart.",
    "example_es": "Tiene el corazón encogido."
  },
  {
    "en": "A bone to pick with someone",
    "es": "Tener algo que reprochar a alguien",
    "ipa": "/ə boʊn tuː pɪk wɪð ˈsʌmwʌn/",
    "example": "He's got a bone to pick with you.",
    "example_es": "Tiene algo que reprocharte."
  },
  {
    "en": "A lump in your throat",
    "es": "Tener un nudo en la garganta (emocional)",
    "ipa": "/ə lʌmp ɪn jɔːr θroʊt/",
    "example": "She's got a lump in her throat.",
    "example_es": "Tiene un nudo en la garganta."
  },
  {
    "en": "A green thumb",
    "es": "Tener mano para las plantas",
    "ipa": "/ə ɡriːn θʌm/",
    "example": "She's got a green thumb.",
    "example_es": "Tiene mano para las plantas."
  },
  {
    "en": "A sweet tooth",
    "es": "Ser goloso",
    "ipa": "/ə swiːt tuːθ/",
    "example": "He's got a sweet tooth.",
    "example_es": "Es goloso."
  },
  {
    "en": "A sharp tongue",
    "es": "Tener la lengua afilada",
    "ipa": "/ə ʃɑːrp tʌŋ/",
    "example": "She's got a sharp tongue.",
    "example_es": "Tiene la lengua afilada."
  },
  {
    "en": "A big head",
    "es": "Ser engreído / Creído",
    "ipa": "/ə bɪɡ hed/",
    "example": "He's got a big head.",
    "example_es": "Es engreído."
  },
  {
    "en": "Bite your tongue",
    "es": "Morderse la lengua",
    "ipa": "/baɪt jɔːr tʌŋ/",
    "example": "I had to bite my tongue to avoid saying something rude.",
    "example_es": "Tuve que morderme la lengua para no decir algo grosero."
  },
  {
    "en": "Blow off steam",
    "es": "Desahogarse",
    "ipa": "/bloʊ ɒf stiːm/",
    "example": "I like to go for a run to blow off steam.",
    "example_es": "Me gusta salir a correr para desahogarme."
  },
  {
    "en": "Bury your head in the sand",
    "es": "Esconder la cabeza bajo tierra",
    "ipa": "/ˈberi jɔːr hed ɪn ðə sænd/",
    "example": "You can't just bury your head in the sand and hope the problem goes away.",
    "example_es": "No puedes simplemente esconder la cabeza bajo tierra y esperar que el problema desaparezca."
  },
  {
    "en": "Carry a torch for someone",
    "es": "Estar enamorado de alguien (en secreto)",
    "ipa": "/ˈkæri ə tɔːrtʃ fɔːr ˈsʌmwʌn/",
    "example": "He still carries a torch for his ex-girlfriend.",
    "example_es": "Todavía está enamorado de su ex-novia."
  },
  {
    "en": "Down in the dumps",
    "es": "Deprimido / Triste",
    "ipa": "/daʊn ɪn ðə dʌmps/",
    "example": "She's been down in the dumps ever since her cat died.",
    "example_es": "Ha estado deprimida desde que murió su gato."
  },
  {
    "en": "Get cold feet",
    "es": "Echarse para atrás / Acobardarse",
    "ipa": "/ɡet koʊld fiːt/",
    "example": "He got cold feet before the wedding.",
    "example_es": "Se acobardó antes de la boda."
  },
  {
    "en": "Get something off your chest",
    "es": "Desahogarse / Quitarse un peso de encima",
    "ipa": "/ɡet ˈsʌmθɪŋ ɒf jɔːr tʃest/",
    "example": "I need to get something off my chest.",
    "example_es": "Necesito desahogarme."
  },
  {
    "en": "Have a chip on your shoulder",
    "es": "Estar resentido / Guardar rencor",
    "ipa": "/hæv ə tʃɪp ɒn jɔːr ˈʃoʊldər/",
    "example": "He has a chip on his shoulder about not getting promoted.",
    "example_es": "Está resentido por no haber sido ascendido."
  },
  {
    "en": "Have a cow",
    "es": "Enfadarse mucho",
    "ipa": "/hæv ə kaʊ/",
    "example": "Don't have a cow, it's just a small scratch.",
    "example_es": "No te enfades tanto, es solo un pequeño rasguño."
  },
  {
    "en": "Have a long face",
    "es": "Tener cara larga / Estar triste",
    "ipa": "/hæv ə lɒŋ feɪs/",
    "example": "Why do you have such a long face?",
    "example_es": "¿Por qué tienes esa cara larga?"
  },
  {
    "en": "In a bad mood",
    "es": "De mal humor",
    "ipa": "/ɪn ə bæd muːd/",
    "example": "He's been in a bad mood all day.",
    "example_es": "Ha estado de mal humor todo el día."
  },
  {
    "en": "In high spirits",
    "es": "De buen humor / Animado",
    "ipa": "/ɪn haɪ ˈspɪrɪts/",
    "example": "She's in high spirits today.",
    "example_es": "Está de buen humor hoy."
  },
  {
    "en": "Keep a straight face",
    "es": "Mantener la seriedad / No reírse",
    "ipa": "/kiːp ə streɪt feɪs/",
    "example": "It was hard to keep a straight face when he told that joke.",
    "example_es": "Fue difícil mantener la seriedad cuando contó ese chiste."
  },
  {
    "en": "Lose your temper",
    "es": "Perder los estribos / Enfadarse",
    "ipa": "/luːz jɔːr ˈtempər/",
    "example": "He lost his temper and started shouting.",
    "example_es": "Perdió los estribos y empezó a gritar."
  },
  {
    "en": "Make your blood boil",
    "es": "Hacerte hervir la sangre",
    "ipa": "/meɪk jɔːr blʌd bɔɪl/",
    "example": "His arrogance really makes my blood boil.",
    "example_es": "Su arrogancia realmente me hace hervir la sangre."
  },
  {
    "en": "On edge",
    "es": "Nervioso / Inquieto",
    "ipa": "/ɒn edʒ/",
    "example": "She's been on edge all day waiting for the results.",
    "example_es": "Ha estado nerviosa todo el día esperando los resultados."
  },
  {
    "en": "Over the moon",
    "es": "Loco de contento / Muy feliz",
    "ipa": "/ˈoʊvər ðə muːn/",
    "example": "She was over the moon when she got the job.",
    "example_es": "Estaba loca de contento cuando consiguió el trabajo."
  },
  {
    "en": "Pull yourself together",
    "es": "Serenarse / Calmarse",
    "ipa": "/pʊl jɔːrˈself təˈɡeðər/",
    "example": "Come on, pull yourself together!",
    "example_es": "¡Vamos, serénate!"
  },
  {
    "en": "See red",
    "es": "Ver todo rojo / Enfadarse mucho",
    "ipa": "/siː red/",
    "example": "When he insulted her, she just saw red.",
    "example_es": "Cuando la insultó, ella simplemente vio todo rojo."
  },
  {
    "en": "Shake like a leaf",
    "es": "Temblar como una hoja",
    "ipa": "/ʃeɪk laɪk ə liːf/",
    "example": "He was shaking like a leaf after the accident.",
    "example_es": "Estaba temblando como una hoja después del accidente."
  },
  {
    "en": "Stab someone in the back",
    "es": "Apuñalar por la espalda",
    "ipa": "/stæb ˈsʌmwʌn ɪn ðə bæk/",
    "example": "I can't believe he stabbed me in the back like that.",
    "example_es": "No puedo creer que me apuñalara por la espalda de esa manera."
  },
  {
    "en": "Take something to heart",
    "es": "Tomarse algo a pecho",
    "ipa": "/teɪk ˈsʌmθɪŋ tuː hɑːrt/",
    "example": "Don't take his criticism to heart.",
    "example_es": "No te tomes sus críticas a pecho."
  },
  {
    "en": "Up in arms",
    "es": "En pie de guerra / Indignado",
    "ipa": "/ʌp ɪn ɑːrmz/",
    "example": "The residents are up in arms about the new development.",
    "example_es": "Los residentes están en pie de guerra por el nuevo desarrollo."
  },
  {
    "en": "Wear your heart on your sleeve",
    "es": "Llevar el corazón en la mano",
    "ipa": "/weər jɔːr hɑːrt ɒn jɔːr sliːv/",
    "example": "She wears her heart on her sleeve, so you always know how she's feeling.",
    "example_es": "Ella lleva el corazón en la mano, así que siempre sabes cómo se siente."
  },
  {
    "en": "Be beside yourself",
    "es": "Estar fuera de sí",
    "ipa": "/biː bɪˈsaɪd jɔːrˈself/",
    "example": "She was beside herself with grief.",
    "example_es": "Estaba fuera de sí de dolor."
  },
  {
    "en": "Have a soft spot for",
    "es": "Tener debilidad por",
    "ipa": "/hæv ə sɒft spɒt fɔːr/",
    "example": "I have a soft spot for old romantic movies.",
    "example_es": "Tengo debilidad por las viejas películas románticas."
  },
  {
    "en": "Be in two minds",
    "es": "Estar indeciso",
    "ipa": "/biː ɪn tuː maɪndz/",
    "example": "I'm in two minds about whether to go or not.",
    "example_es": "Estoy indeciso sobre si ir o no."
  },
  {
    "en": "Have a whale of a time",
    "es": "Pasárselo en grande",
    "ipa": "/hæv ə weɪl ɒv ə taɪm/",
    "example": "We had a whale of a time at the party.",
    "example_es": "Nos lo pasamos en grande en la fiesta."
  },
  {
    "en": "Be on top of the world",
    "es": "Estar en la cima del mundo",
    "ipa": "/bi ɒn tɒp ɒv ðə wɜːrld/",
    "example": "She was on top of the world after winning the competition.",
    "example_es": "Estaba en la cima del mundo después de ganar la competición."
  }
]